{
  "name": "Tagliatelle Tricolore",
  "slug": "tagliatelle-tricolore",
  "image": "",
  "recipeYield": 4,
  "recipeIngredient": [
    {
      "name": "tagliatelle",
      "amount": 400,
      "unit": "g"
    },
    {
      "name": "courgettes",
      "amount": 2,
      "unit": "stuk"
    },
    {
      "name": "paprika",
      "amount": 2,
      "unit": "stuk"
    },
    {
      "name": "kerstomaatjes",
      "amount": 1,
      "unit": "bakje"
    },
    {
      "name": "oranje pesto",
      "amount": 1,
      "unit": "potje"
    },
    {
      "name": "olijfolie",
      "amount": 3,
      "unit": "el"
    }
  ],
  "recipeInstructions": [
    {
      "text": "Snijd de paprika's in reepjes, de courgettes in halve maantjes en halveer de kerstomaatjes"
    },
    {
      "text": "Verhit de olijfolie in een grote hapjespan en bak de paprika"
    },
    {
      "text": "Voeg de courgette toe en bak mee"
    },
    {
      "text": "Voeg de kerstomaatjes toe"
    },
    {
      "text": "Roer de oranje pesto erdoor"
    },
    {
      "text": "Kook intussen de tagliatelle volgens de verpakking"
    },
    {
      "text": "Schep de uitgelekte pasta door de groenten en meng goed"
    }
  ],
  "recipeCuisine": "Italiaans"
}
